[{"fields": {"model": "contenttype", "app_label": "contenttypes"}, "model": "contenttypes.contenttype", "pk": 1}, {"fields": {"model": "group", "app_label": "auth"}, "model": "contenttypes.contenttype", "pk": 2}, {"fields": {"model": "user", "app_label": "auth"}, "model": "contenttypes.contenttype", "pk": 3}, {"fields": {"model": "permission", "app_label": "auth"}, "model": "contenttypes.contenttype", "pk": 4}, {"fields": {"model": "session", "app_label": "sessions"}, "model": "contenttypes.contenttype", "pk": 5}, {"fields": {"model": "logentry", "app_label": "admin"}, "model": "contenttypes.contenttype", "pk": 6}, {"fields": {"model": "bindserver", "app_label": "binder"}, "model": "contenttypes.contenttype", "pk": 7}, {"fields": {"model": "key", "app_label": "binder"}, "model": "contenttypes.contenttype", "pk": 8}, {"fields": {"codename": "add_contenttype", "name": "Can add content type", "content_type": 1}, "model": "auth.permission", "pk": 1}, {"fields": {"codename": "change_contenttype", "name": "Can change content type", "content_type": 1}, "model": "auth.permission", "pk": 2}, {"fields": {"codename": "delete_contenttype", "name": "Can delete content type", "content_type": 1}, "model": "auth.permission", "pk": 3}, {"fields": {"codename": "add_permission", "name": "Can add permission", "content_type": 4}, "model": "auth.permission", "pk": 4}, {"fields": {"codename": "change_permission", "name": "Can change permission", "content_type": 4}, "model": "auth.permission", "pk": 5}, {"fields": {"codename": "delete_permission", "name": "Can delete permission", "content_type": 4}, "model": "auth.permission", "pk": 6}, {"fields": {"codename": "add_group", "name": "Can add group", "content_type": 2}, "model": "auth.permission", "pk": 7}, {"fields": {"codename": "change_group", "name": "Can change group", "content_type": 2}, "model": "auth.permission", "pk": 8}, {"fields": {"codename": "delete_group", "name": "Can delete group", "content_type": 2}, "model": "auth.permission", "pk": 9}, {"fields": {"codename": "add_user", "name": "Can add user", "content_type": 3}, "model": "auth.permission", "pk": 10}, {"fields": {"codename": "change_user", "name": "Can change user", "content_type": 3}, "model": "auth.permission", "pk": 11}, {"fields": {"codename": "delete_user", "name": "Can delete user", "content_type": 3}, "model": "auth.permission", "pk": 12}, {"fields": {"codename": "add_session", "name": "Can add session", "content_type": 5}, "model": "auth.permission", "pk": 13}, {"fields": {"codename": "change_session", "name": "Can change session", "content_type": 5}, "model": "auth.permission", "pk": 14}, {"fields": {"codename": "delete_session", "name": "Can delete session", "content_type": 5}, "model": "auth.permission", "pk": 15}, {"fields": {"codename": "add_logentry", "name": "Can add log entry", "content_type": 6}, "model": "auth.permission", "pk": 16}, {"fields": {"codename": "change_logentry", "name": "Can change log entry", "content_type": 6}, "model": "auth.permission", "pk": 17}, {"fields": {"codename": "delete_logentry", "name": "Can delete log entry", "content_type": 6}, "model": "auth.permission", "pk": 18}, {"fields": {"codename": "add_key", "name": "Can add key", "content_type": 8}, "model": "auth.permission", "pk": 19}, {"fields": {"codename": "change_key", "name": "Can change key", "content_type": 8}, "model": "auth.permission", "pk": 20}, {"fields": {"codename": "delete_key", "name": "Can delete key", "content_type": 8}, "model": "auth.permission", "pk": 21}, {"fields": {"codename": "add_bindserver", "name": "Can add bind server", "content_type": 7}, "model": "auth.permission", "pk": 22}, {"fields": {"codename": "change_bindserver", "name": "Can change bind server", "content_type": 7}, "model": "auth.permission", "pk": 23}, {"fields": {"codename": "delete_bindserver", "name": "Can delete bind server", "content_type": 7}, "model": "auth.permission", "pk": 24}, {"fields": {"username": "admin", "first_name": "", "last_name": "", "is_active": true, "is_superuser": true, "is_staff": true, "last_login": null, "groups": [], "user_permissions": [], "password": "pbkdf2_sha256$20000$7zHgdrWNLW4j$vjAbJsyiSd3UXo7+MItoh9amW/N+tD8hls/BsXdDDnI=", "email": "admin@example.org", "date_joined": "2016-12-05T08:44:01.676"}, "model": "auth.user", "pk": 1}]